MANIFEST.in
README.rst
setup.py
cp1147/__init__.py
cp1147/cp1147.py
cp1147.egg-info/PKG-INFO
cp1147.egg-info/SOURCES.txt
cp1147.egg-info/dependency_links.txt
cp1147.egg-info/top_level.txt