Metadata-Version: 1.1
Name: cp1147
Version: 1.0
Summary: cp1147 EBCDIC french (euro) codec
Home-page: http://www.datim.fr
Author: Denis Wallerich
Author-email: denis.wallerich@datim.fr
License: BSD
Platform: UNKNOWN
Classifier: Development Status :: 5 - Production/Stable
Classifier: Topic :: System :: Hardware :: Mainframes
Classifier: License :: OSI Approved :: BSD License
